catkin_tools/__init__.py
catkin_tools/argument_parsing.py
catkin_tools/common.py
catkin_tools/config.py
catkin_tools/context.py
catkin_tools/metadata.py
catkin_tools/resultspace.py
catkin_tools/terminal_color.py
catkin_tools/utils.py
catkin_tools/commands/__init__.py
catkin_tools/commands/catkin.py
catkin_tools/execution/__init__.py
catkin_tools/execution/controllers.py
catkin_tools/execution/events.py
catkin_tools/execution/executor.py
catkin_tools/execution/io.py
catkin_tools/execution/job_server.py
catkin_tools/execution/jobs.py
catkin_tools/execution/stages.py
catkin_tools/jobs/__init__.py
catkin_tools/jobs/catkin.py
catkin_tools/jobs/cmake.py
catkin_tools/jobs/utils.py
catkin_tools/jobs/cmake/python.cmake
catkin_tools/jobs/cmake/python_install_dir.cmake
catkin_tools/jobs/commands/__init__.py
catkin_tools/jobs/commands/cmake.py
catkin_tools/jobs/commands/make.py
catkin_tools/notifications/__init__.py
catkin_tools/notifications/impl.py
catkin_tools/notifications/resources/linux/catkin_icon.png
catkin_tools/notifications/resources/linux/catkin_icon_red.png
catkin_tools/spaces/__init__.py
catkin_tools/spaces/build.py
catkin_tools/spaces/devel.py
catkin_tools/spaces/install.py
catkin_tools/spaces/log.py
catkin_tools/spaces/source.py
catkin_tools/verbs/__init__.py
catkin_tools/verbs/catkin_shell_verbs.bash
catkin_tools/verbs/catkin_build/__init__.py
catkin_tools/verbs/catkin_build/build.py
catkin_tools/verbs/catkin_build/cli.py
catkin_tools/verbs/catkin_build/color.py
catkin_tools/verbs/catkin_clean/__init__.py
catkin_tools/verbs/catkin_clean/clean.py
catkin_tools/verbs/catkin_clean/cli.py
catkin_tools/verbs/catkin_config/__init__.py
catkin_tools/verbs/catkin_config/cli.py
catkin_tools/verbs/catkin_create/__init__.py
catkin_tools/verbs/catkin_create/cli.py
catkin_tools/verbs/catkin_env/__init__.py
catkin_tools/verbs/catkin_env/cli.py
catkin_tools/verbs/catkin_init/__init__.py
catkin_tools/verbs/catkin_init/cli.py
catkin_tools/verbs/catkin_list/__init__.py
catkin_tools-0.9.5.dist-info/LICENSE
catkin_tools-0.9.5.dist-info/METADATA
catkin_tools-0.9.5.dist-info/WHEEL
catkin_tools-0.9.5.dist-info/entry_points.txt
catkin_tools-0.9.5.dist-info/top_level.txt
catkin_tools-0.9.5.dist-info/RECORD
