Metadata-Version: 2.1
Name: catkin-tools
Version: 0.9.5
Summary: Command line tools for working with catkin.
Home-page: https://catkin-tools.readthedocs.org/
Author: William Woodall
Author-email: william@osrfoundation.org
Maintainer: William Woodall
Maintainer-email: william@osrfoundation.org
License: Apache 2.0
Keywords: catkin
Classifier: Environment :: Console
Classifier: Intended Audience :: Developers
Classifier: License :: OSI Approved :: Apache Software License
Classifier: Programming Language :: Python
Requires-Python: >=3.5
License-File: LICENSE
Requires-Dist: PyYAML
Requires-Dist: catkin-pkg >=0.3.0
Requires-Dist: osrf-pycommon >0.1.1
Requires-Dist: setuptools
